voir/__init__.py
voir/__main__.py
voir/argparse_ext.py
voir/cli.py
voir/helpers.py
voir/overseer.py
voir/phase.py
voir/proc.py
voir/scriptutils.py
voir/smuggle.py
voir/tools.py
voir/version.py
voir/instruments/__init__.py
voir/instruments/cpu.py
voir/instruments/dash.py
voir/instruments/io.py
voir/instruments/log.py
voir/instruments/manage.py
voir/instruments/metric.py
voir/instruments/monitor.py
voir/instruments/network.py
voir/instruments/utils.py
voir/instruments/gpu/__init__.py
voir/instruments/gpu/common.py
voir/instruments/gpu/cpu.py
voir/instruments/gpu/cuda.py
voir/instruments/gpu/hpu.py
voir/instruments/gpu/rocm.py
voir/instruments/gpu/xpu.py
voir-0.2.23.dist-info/METADATA
voir-0.2.23.dist-info/WHEEL
voir-0.2.23.dist-info/entry_points.txt
voir-0.2.23.dist-info/RECORD
