Metadata-Version: 2.4
Name: voir
Version: 0.2.23
Summary: Instrument, extend and visualize your programs
Author-email: Olivier Breuleux <breuleux@gmail.com>
License-Expression: MIT
Requires-Python: >=3.8
Requires-Dist: giving>=0.4.2
Requires-Dist: omegaconf>=2.3.0
Requires-Dist: ovld<0.4.0,>=0.3.2
Requires-Dist: psutil>=7.0.0
Requires-Dist: ptera>=1.4.1
Requires-Dist: rich>=13.9.4
Provides-Extra: cuda
Requires-Dist: nvidia-ml-py>=12.570.86; extra == 'cuda'
